{
  "updated": "2026-06-22T22:08:36.007051Z",
  "dashboard": [
    {
      "gebied": "Basel",
      "pegel_05": null,
      "pegel_13": null,
      "pegel_21": null
    },
    {
      "gebied": "Maxau",
      "pegel_05": null,
      "pegel_13": null,
      "pegel_21": null
    },
    {
      "gebied": "Oestrich",
      "pegel_05": null,
      "pegel_13": null,
      "pegel_21": null
    },
    {
      "gebied": "Kaub",
      "pegel_05": null,
      "pegel_13": null,
      "pegel_21": null
    },
    {
      "gebied": "Koblenz",
      "pegel_05": null,
      "pegel_13": null,
      "pegel_21": null
    },
    {
      "gebied": "Keulen",
      "pegel_05": null,
      "pegel_13": null,
      "pegel_21": null
    },
    {
      "gebied": "Dusseldorf",
      "pegel_05": null,
      "pegel_13": null,
      "pegel_21": null
    },
    {
      "gebied": "Duisburg",
      "pegel_05": null,
      "pegel_13": null,
      "pegel_21": null
    },
    {
      "gebied": "Wesel",
      "pegel_05": null,
      "pegel_13": null,
      "pegel_21": null
    },
    {
      "gebied": "Nijmegen",
      "pegel_05": null,
      "pegel_13": null,
      "pegel_21": null,
      "pegel_nu": 534
    }
  ],
  "forecasts": {
    "Oestrich": {
      "station": "Oestrich",
      "dates": [
        "22.06.2026",
        "23.06.2026",
        "24.06.2026",
        "25.06.2026",
        "26.06.2026",
        "27.06.2026"
      ],
      "hourly": [
        {
          "uur": "03:00",
          "22.06.2026": null,
          "23.06.2026": null,
          "24.06.2026": null,
          "25.06.2026": null,
          "26.06.2026": 116,
          "27.06.2026": 108
        },
        {
          "uur": "05:00",
          "22.06.2026": 114,
          "23.06.2026": null,
          "24.06.2026": null,
          "25.06.2026": null,
          "26.06.2026": 116,
          "27.06.2026": 107
        },
        {
          "uur": "07:00",
          "22.06.2026": null,
          "23.06.2026": null,
          "24.06.2026": null,
          "25.06.2026": null,
          "26.06.2026": 116,
          "27.06.2026": 106
        },
        {
          "uur": "09:00",
          "22.06.2026": null,
          "23.06.2026": null,
          "24.06.2026": null,
          "25.06.2026": null,
          "26.06.2026": 115,
          "27.06.2026": null
        },
        {
          "uur": "11:00",
          "22.06.2026": null,
          "23.06.2026": null,
          "24.06.2026": null,
          "25.06.2026": null,
          "26.06.2026": 114,
          "27.06.2026": null
        },
        {
          "uur": "13:00",
          "22.06.2026": 118,
          "23.06.2026": null,
          "24.06.2026": null,
          "25.06.2026": null,
          "26.06.2026": 114,
          "27.06.2026": null
        },
        {
          "uur": "15:00",
          "22.06.2026": null,
          "23.06.2026": null,
          "24.06.2026": null,
          "25.06.2026": null,
          "26.06.2026": 113,
          "27.06.2026": null
        },
        {
          "uur": "17:00",
          "22.06.2026": null,
          "23.06.2026": null,
          "24.06.2026": null,
          "25.06.2026": null,
          "26.06.2026": 112,
          "27.06.2026": null
        },
        {
          "uur": "19:00",
          "22.06.2026": null,
          "23.06.2026": null,
          "24.06.2026": null,
          "25.06.2026": null,
          "26.06.2026": 111,
          "27.06.2026": null
        },
        {
          "uur": "21:00",
          "22.06.2026": 116,
          "23.06.2026": null,
          "24.06.2026": null,
          "25.06.2026": null,
          "26.06.2026": 110,
          "27.06.2026": null
        },
        {
          "uur": "23:00",
          "22.06.2026": null,
          "23.06.2026": null,
          "24.06.2026": null,
          "25.06.2026": null,
          "26.06.2026": 109,
          "27.06.2026": null
        }
      ]
    },
    "Kaub": {
      "station": "Kaub",
      "dates": [
        "22.06.2026",
        "23.06.2026",
        "24.06.2026",
        "25.06.2026",
        "26.06.2026",
        "27.06.2026"
      ],
      "hourly": [
        {
          "uur": "03:00",
          "22.06.2026": null,
          "23.06.2026": null,
          "24.06.2026": null,
          "25.06.2026": null,
          "26.06.2026": 107,
          "27.06.2026": 100
        },
        {
          "uur": "05:00",
          "22.06.2026": 103,
          "23.06.2026": null,
          "24.06.2026": null,
          "25.06.2026": null,
          "26.06.2026": 107,
          "27.06.2026": 100
        },
        {
          "uur": "07:00",
          "22.06.2026": null,
          "23.06.2026": null,
          "24.06.2026": null,
          "25.06.2026": null,
          "26.06.2026": 106,
          "27.06.2026": 99
        },
        {
          "uur": "09:00",
          "22.06.2026": null,
          "23.06.2026": null,
          "24.06.2026": null,
          "25.06.2026": null,
          "26.06.2026": 106,
          "27.06.2026": null
        },
        {
          "uur": "11:00",
          "22.06.2026": null,
          "23.06.2026": null,
          "24.06.2026": null,
          "25.06.2026": null,
          "26.06.2026": 106,
          "27.06.2026": null
        },
        {
          "uur": "13:00",
          "22.06.2026": 106,
          "23.06.2026": null,
          "24.06.2026": null,
          "25.06.2026": null,
          "26.06.2026": 105,
          "27.06.2026": null
        },
        {
          "uur": "15:00",
          "22.06.2026": null,
          "23.06.2026": null,
          "24.06.2026": null,
          "25.06.2026": null,
          "26.06.2026": 105,
          "27.06.2026": null
        },
        {
          "uur": "17:00",
          "22.06.2026": null,
          "23.06.2026": null,
          "24.06.2026": null,
          "25.06.2026": null,
          "26.06.2026": 104,
          "27.06.2026": null
        },
        {
          "uur": "19:00",
          "22.06.2026": null,
          "23.06.2026": null,
          "24.06.2026": null,
          "25.06.2026": null,
          "26.06.2026": 104,
          "27.06.2026": null
        },
        {
          "uur": "21:00",
          "22.06.2026": 108,
          "23.06.2026": null,
          "24.06.2026": null,
          "25.06.2026": null,
          "26.06.2026": 103,
          "27.06.2026": null
        },
        {
          "uur": "23:00",
          "22.06.2026": null,
          "23.06.2026": null,
          "24.06.2026": null,
          "25.06.2026": null,
          "26.06.2026": 102,
          "27.06.2026": null
        }
      ]
    },
    "Keulen": {
      "station": "Keulen",
      "dates": [
        "22.06.2026",
        "23.06.2026",
        "24.06.2026",
        "25.06.2026",
        "26.06.2026",
        "27.06.2026"
      ],
      "hourly": [
        {
          "uur": "03:00",
          "22.06.2026": null,
          "23.06.2026": null,
          "24.06.2026": null,
          "25.06.2026": null,
          "26.06.2026": 154,
          "27.06.2026": 155
        },
        {
          "uur": "05:00",
          "22.06.2026": 156,
          "23.06.2026": null,
          "24.06.2026": null,
          "25.06.2026": null,
          "26.06.2026": 154,
          "27.06.2026": 154
        },
        {
          "uur": "07:00",
          "22.06.2026": null,
          "23.06.2026": null,
          "24.06.2026": null,
          "25.06.2026": null,
          "26.06.2026": 155,
          "27.06.2026": 154
        },
        {
          "uur": "09:00",
          "22.06.2026": null,
          "23.06.2026": null,
          "24.06.2026": null,
          "25.06.2026": null,
          "26.06.2026": 155,
          "27.06.2026": null
        },
        {
          "uur": "11:00",
          "22.06.2026": null,
          "23.06.2026": null,
          "24.06.2026": null,
          "25.06.2026": null,
          "26.06.2026": 155,
          "27.06.2026": null
        },
        {
          "uur": "13:00",
          "22.06.2026": 156,
          "23.06.2026": null,
          "24.06.2026": null,
          "25.06.2026": null,
          "26.06.2026": 155,
          "27.06.2026": null
        },
        {
          "uur": "15:00",
          "22.06.2026": null,
          "23.06.2026": null,
          "24.06.2026": null,
          "25.06.2026": null,
          "26.06.2026": 155,
          "27.06.2026": null
        },
        {
          "uur": "17:00",
          "22.06.2026": null,
          "23.06.2026": null,
          "24.06.2026": null,
          "25.06.2026": null,
          "26.06.2026": 155,
          "27.06.2026": null
        },
        {
          "uur": "19:00",
          "22.06.2026": null,
          "23.06.2026": null,
          "24.06.2026": null,
          "25.06.2026": null,
          "26.06.2026": 155,
          "27.06.2026": null
        },
        {
          "uur": "21:00",
          "22.06.2026": null,
          "23.06.2026": null,
          "24.06.2026": null,
          "25.06.2026": null,
          "26.06.2026": 155,
          "27.06.2026": null
        },
        {
          "uur": "23:00",
          "22.06.2026": null,
          "23.06.2026": null,
          "24.06.2026": null,
          "25.06.2026": null,
          "26.06.2026": 155,
          "27.06.2026": null
        }
      ]
    },
    "Duisburg": {
      "station": "Duisburg",
      "dates": [
        "22.06.2026",
        "23.06.2026",
        "24.06.2026",
        "25.06.2026",
        "26.06.2026",
        "27.06.2026"
      ],
      "hourly": [
        {
          "uur": "03:00",
          "22.06.2026": null,
          "23.06.2026": null,
          "24.06.2026": null,
          "25.06.2026": null,
          "26.06.2026": 244,
          "27.06.2026": 242
        },
        {
          "uur": "05:00",
          "22.06.2026": 251,
          "23.06.2026": null,
          "24.06.2026": null,
          "25.06.2026": null,
          "26.06.2026": 244,
          "27.06.2026": 242
        },
        {
          "uur": "07:00",
          "22.06.2026": null,
          "23.06.2026": null,
          "24.06.2026": null,
          "25.06.2026": null,
          "26.06.2026": 243,
          "27.06.2026": 242
        },
        {
          "uur": "09:00",
          "22.06.2026": null,
          "23.06.2026": null,
          "24.06.2026": null,
          "25.06.2026": null,
          "26.06.2026": 243,
          "27.06.2026": null
        },
        {
          "uur": "11:00",
          "22.06.2026": null,
          "23.06.2026": null,
          "24.06.2026": null,
          "25.06.2026": null,
          "26.06.2026": 242,
          "27.06.2026": null
        },
        {
          "uur": "13:00",
          "22.06.2026": 251,
          "23.06.2026": null,
          "24.06.2026": null,
          "25.06.2026": null,
          "26.06.2026": 242,
          "27.06.2026": null
        },
        {
          "uur": "15:00",
          "22.06.2026": null,
          "23.06.2026": null,
          "24.06.2026": null,
          "25.06.2026": null,
          "26.06.2026": 242,
          "27.06.2026": null
        },
        {
          "uur": "17:00",
          "22.06.2026": null,
          "23.06.2026": null,
          "24.06.2026": null,
          "25.06.2026": null,
          "26.06.2026": 242,
          "27.06.2026": null
        },
        {
          "uur": "19:00",
          "22.06.2026": null,
          "23.06.2026": null,
          "24.06.2026": null,
          "25.06.2026": null,
          "26.06.2026": 242,
          "27.06.2026": null
        },
        {
          "uur": "21:00",
          "22.06.2026": null,
          "23.06.2026": null,
          "24.06.2026": null,
          "25.06.2026": null,
          "26.06.2026": 242,
          "27.06.2026": null
        },
        {
          "uur": "23:00",
          "22.06.2026": null,
          "23.06.2026": null,
          "24.06.2026": null,
          "25.06.2026": null,
          "26.06.2026": 242,
          "27.06.2026": null
        }
      ]
    }
  },
  "nijmegen": {
    "current": 534,
    "forecast_raw": {}
  },
  "maxau_hourly": [
    {
      "t": "22-06 10:15",
      "v": 398
    },
    {
      "t": "22-06 10:30",
      "v": 399
    },
    {
      "t": "22-06 10:45",
      "v": 400
    },
    {
      "t": "22-06 11:00",
      "v": 401
    },
    {
      "t": "22-06 11:15",
      "v": 400
    },
    {
      "t": "22-06 11:30",
      "v": 400
    },
    {
      "t": "22-06 11:45",
      "v": 400
    },
    {
      "t": "22-06 12:00",
      "v": 400
    },
    {
      "t": "22-06 12:15",
      "v": 401
    },
    {
      "t": "22-06 12:30",
      "v": 403
    },
    {
      "t": "22-06 12:45",
      "v": 400
    },
    {
      "t": "22-06 13:00",
      "v": 401
    },
    {
      "t": "22-06 13:15",
      "v": 400
    },
    {
      "t": "22-06 13:30",
      "v": 400
    },
    {
      "t": "22-06 13:45",
      "v": 401
    },
    {
      "t": "22-06 14:00",
      "v": 401
    },
    {
      "t": "22-06 14:15",
      "v": 401
    },
    {
      "t": "22-06 14:30",
      "v": 400
    },
    {
      "t": "22-06 14:45",
      "v": 400
    },
    {
      "t": "22-06 15:00",
      "v": 401
    },
    {
      "t": "22-06 15:15",
      "v": 400
    },
    {
      "t": "22-06 15:30",
      "v": 401
    },
    {
      "t": "22-06 15:45",
      "v": 401
    },
    {
      "t": "22-06 16:00",
      "v": 400
    },
    {
      "t": "22-06 16:15",
      "v": 399
    },
    {
      "t": "22-06 16:30",
      "v": 399
    },
    {
      "t": "22-06 16:45",
      "v": 399
    },
    {
      "t": "22-06 17:00",
      "v": 399
    },
    {
      "t": "22-06 17:15",
      "v": 398
    },
    {
      "t": "22-06 17:30",
      "v": 398
    },
    {
      "t": "22-06 17:45",
      "v": 398
    },
    {
      "t": "22-06 18:00",
      "v": 398
    },
    {
      "t": "22-06 18:15",
      "v": 395
    },
    {
      "t": "22-06 18:30",
      "v": 398
    },
    {
      "t": "22-06 18:45",
      "v": 396
    },
    {
      "t": "22-06 19:00",
      "v": 395
    },
    {
      "t": "22-06 19:15",
      "v": 397
    },
    {
      "t": "22-06 19:30",
      "v": 395
    },
    {
      "t": "22-06 19:45",
      "v": 393
    },
    {
      "t": "22-06 20:00",
      "v": 395
    },
    {
      "t": "22-06 20:15",
      "v": 394
    },
    {
      "t": "22-06 20:30",
      "v": 394
    },
    {
      "t": "22-06 20:45",
      "v": 395
    },
    {
      "t": "22-06 21:00",
      "v": 394
    },
    {
      "t": "22-06 21:15",
      "v": 391
    },
    {
      "t": "22-06 21:30",
      "v": 392
    },
    {
      "t": "22-06 21:45",
      "v": 392
    },
    {
      "t": "22-06 22:00",
      "v": 392
    }
  ]
}