{
  "updated": "2026-07-13T19:37:11.559628Z",
  "dashboard": [
    {
      "gebied": "Basel",
      "pegel_05": 73,
      "pegel_13": 80,
      "pegel_21": 82
    },
    {
      "gebied": "Maxau",
      "pegel_05": 147,
      "pegel_13": 149,
      "pegel_21": 143
    },
    {
      "gebied": "Oestrich",
      "pegel_05": 71,
      "pegel_13": 73,
      "pegel_21": 73
    },
    {
      "gebied": "Kaub",
      "pegel_05": 53,
      "pegel_13": 53,
      "pegel_21": 55
    },
    {
      "gebied": "Koblenz",
      "pegel_05": 106,
      "pegel_13": 106,
      "pegel_21": 102
    },
    {
      "gebied": "Keulen",
      "pegel_05": 98,
      "pegel_13": 97,
      "pegel_21": 96
    },
    {
      "gebied": "Dusseldorf",
      "pegel_05": 57,
      "pegel_13": 54,
      "pegel_21": 53
    },
    {
      "gebied": "Duisburg",
      "pegel_05": 188,
      "pegel_13": 185,
      "pegel_21": 183
    },
    {
      "gebied": "Wesel",
      "pegel_05": null,
      "pegel_13": 33,
      "pegel_21": null
    },
    {
      "gebied": "Nijmegen",
      "pegel_05": null,
      "pegel_13": null,
      "pegel_21": null,
      "pegel_nu": 470
    }
  ],
  "forecasts": {
    "Oestrich": {
      "station": "Oestrich",
      "dates": [
        "12.07.2026",
        "13.07.2026",
        "14.07.2026",
        "15.07.2026",
        "16.07.2026",
        "17.07.2026"
      ],
      "hourly": [
        {
          "uur": "03:00",
          "12.07.2026": null,
          "13.07.2026": null,
          "14.07.2026": null,
          "15.07.2026": null,
          "16.07.2026": null,
          "17.07.2026": 64
        },
        {
          "uur": "05:00",
          "12.07.2026": 77,
          "13.07.2026": null,
          "14.07.2026": 71,
          "15.07.2026": null,
          "16.07.2026": null,
          "17.07.2026": 64
        },
        {
          "uur": "07:00",
          "12.07.2026": null,
          "13.07.2026": null,
          "14.07.2026": null,
          "15.07.2026": null,
          "16.07.2026": null,
          "17.07.2026": 63
        },
        {
          "uur": "09:00",
          "12.07.2026": null,
          "13.07.2026": null,
          "14.07.2026": null,
          "15.07.2026": null,
          "16.07.2026": null,
          "17.07.2026": 63
        },
        {
          "uur": "11:00",
          "12.07.2026": null,
          "13.07.2026": null,
          "14.07.2026": null,
          "15.07.2026": null,
          "16.07.2026": null,
          "17.07.2026": 63
        },
        {
          "uur": "13:00",
          "12.07.2026": 76,
          "13.07.2026": null,
          "14.07.2026": 71,
          "15.07.2026": null,
          "16.07.2026": null,
          "17.07.2026": 63
        },
        {
          "uur": "15:00",
          "12.07.2026": null,
          "13.07.2026": null,
          "14.07.2026": null,
          "15.07.2026": null,
          "16.07.2026": null,
          "17.07.2026": 63
        },
        {
          "uur": "17:00",
          "12.07.2026": null,
          "13.07.2026": null,
          "14.07.2026": null,
          "15.07.2026": null,
          "16.07.2026": null,
          "17.07.2026": 62
        },
        {
          "uur": "19:00",
          "12.07.2026": null,
          "13.07.2026": null,
          "14.07.2026": null,
          "15.07.2026": null,
          "16.07.2026": null,
          "17.07.2026": 62
        },
        {
          "uur": "21:00",
          "12.07.2026": 73,
          "13.07.2026": null,
          "14.07.2026": 70,
          "15.07.2026": null,
          "16.07.2026": null,
          "17.07.2026": 62
        },
        {
          "uur": "23:00",
          "12.07.2026": null,
          "13.07.2026": null,
          "14.07.2026": null,
          "15.07.2026": null,
          "16.07.2026": 65,
          "17.07.2026": 62
        }
      ]
    },
    "Kaub": {
      "station": "Kaub",
      "dates": [
        "12.07.2026",
        "13.07.2026",
        "14.07.2026",
        "15.07.2026",
        "16.07.2026",
        "17.07.2026"
      ],
      "hourly": [
        {
          "uur": "03:00",
          "12.07.2026": null,
          "13.07.2026": null,
          "14.07.2026": null,
          "15.07.2026": null,
          "16.07.2026": null,
          "17.07.2026": 49
        },
        {
          "uur": "05:00",
          "12.07.2026": 58,
          "13.07.2026": null,
          "14.07.2026": 53,
          "15.07.2026": null,
          "16.07.2026": null,
          "17.07.2026": 48
        },
        {
          "uur": "07:00",
          "12.07.2026": null,
          "13.07.2026": null,
          "14.07.2026": null,
          "15.07.2026": null,
          "16.07.2026": null,
          "17.07.2026": 48
        },
        {
          "uur": "09:00",
          "12.07.2026": null,
          "13.07.2026": null,
          "14.07.2026": null,
          "15.07.2026": null,
          "16.07.2026": null,
          "17.07.2026": 47
        },
        {
          "uur": "11:00",
          "12.07.2026": null,
          "13.07.2026": null,
          "14.07.2026": null,
          "15.07.2026": null,
          "16.07.2026": null,
          "17.07.2026": 47
        },
        {
          "uur": "13:00",
          "12.07.2026": 59,
          "13.07.2026": null,
          "14.07.2026": 53,
          "15.07.2026": null,
          "16.07.2026": null,
          "17.07.2026": 46
        },
        {
          "uur": "15:00",
          "12.07.2026": null,
          "13.07.2026": null,
          "14.07.2026": null,
          "15.07.2026": null,
          "16.07.2026": null,
          "17.07.2026": 46
        },
        {
          "uur": "17:00",
          "12.07.2026": null,
          "13.07.2026": null,
          "14.07.2026": null,
          "15.07.2026": null,
          "16.07.2026": null,
          "17.07.2026": 45
        },
        {
          "uur": "19:00",
          "12.07.2026": null,
          "13.07.2026": null,
          "14.07.2026": null,
          "15.07.2026": null,
          "16.07.2026": null,
          "17.07.2026": 45
        },
        {
          "uur": "21:00",
          "12.07.2026": 57,
          "13.07.2026": null,
          "14.07.2026": 55,
          "15.07.2026": null,
          "16.07.2026": null,
          "17.07.2026": 45
        },
        {
          "uur": "23:00",
          "12.07.2026": null,
          "13.07.2026": null,
          "14.07.2026": null,
          "15.07.2026": null,
          "16.07.2026": 50,
          "17.07.2026": 45
        }
      ]
    },
    "Keulen": {
      "station": "Keulen",
      "dates": [
        "12.07.2026",
        "13.07.2026",
        "14.07.2026",
        "15.07.2026",
        "16.07.2026",
        "17.07.2026"
      ],
      "hourly": [
        {
          "uur": "03:00",
          "12.07.2026": null,
          "13.07.2026": null,
          "14.07.2026": null,
          "15.07.2026": null,
          "16.07.2026": null,
          "17.07.2026": 92
        },
        {
          "uur": "05:00",
          "12.07.2026": 106,
          "13.07.2026": null,
          "14.07.2026": 98,
          "15.07.2026": null,
          "16.07.2026": null,
          "17.07.2026": 92
        },
        {
          "uur": "07:00",
          "12.07.2026": null,
          "13.07.2026": null,
          "14.07.2026": null,
          "15.07.2026": null,
          "16.07.2026": null,
          "17.07.2026": 92
        },
        {
          "uur": "09:00",
          "12.07.2026": null,
          "13.07.2026": null,
          "14.07.2026": null,
          "15.07.2026": null,
          "16.07.2026": null,
          "17.07.2026": 92
        },
        {
          "uur": "11:00",
          "12.07.2026": null,
          "13.07.2026": null,
          "14.07.2026": null,
          "15.07.2026": null,
          "16.07.2026": null,
          "17.07.2026": 92
        },
        {
          "uur": "13:00",
          "12.07.2026": 103,
          "13.07.2026": null,
          "14.07.2026": 97,
          "15.07.2026": null,
          "16.07.2026": null,
          "17.07.2026": 92
        },
        {
          "uur": "15:00",
          "12.07.2026": null,
          "13.07.2026": null,
          "14.07.2026": null,
          "15.07.2026": null,
          "16.07.2026": null,
          "17.07.2026": 92
        },
        {
          "uur": "17:00",
          "12.07.2026": null,
          "13.07.2026": null,
          "14.07.2026": null,
          "15.07.2026": null,
          "16.07.2026": null,
          "17.07.2026": 91
        },
        {
          "uur": "19:00",
          "12.07.2026": null,
          "13.07.2026": null,
          "14.07.2026": null,
          "15.07.2026": null,
          "16.07.2026": null,
          "17.07.2026": 91
        },
        {
          "uur": "21:00",
          "12.07.2026": 100,
          "13.07.2026": null,
          "14.07.2026": 96,
          "15.07.2026": null,
          "16.07.2026": null,
          "17.07.2026": 90
        },
        {
          "uur": "23:00",
          "12.07.2026": null,
          "13.07.2026": null,
          "14.07.2026": null,
          "15.07.2026": null,
          "16.07.2026": 92,
          "17.07.2026": 89
        }
      ]
    },
    "Duisburg": {
      "station": "Duisburg",
      "dates": [
        "12.07.2026",
        "13.07.2026",
        "14.07.2026",
        "15.07.2026",
        "16.07.2026",
        "17.07.2026"
      ],
      "hourly": [
        {
          "uur": "03:00",
          "12.07.2026": null,
          "13.07.2026": null,
          "14.07.2026": null,
          "15.07.2026": null,
          "16.07.2026": null,
          "17.07.2026": 179
        },
        {
          "uur": "05:00",
          "12.07.2026": 195,
          "13.07.2026": null,
          "14.07.2026": 188,
          "15.07.2026": null,
          "16.07.2026": null,
          "17.07.2026": 179
        },
        {
          "uur": "07:00",
          "12.07.2026": null,
          "13.07.2026": null,
          "14.07.2026": null,
          "15.07.2026": null,
          "16.07.2026": null,
          "17.07.2026": 178
        },
        {
          "uur": "09:00",
          "12.07.2026": null,
          "13.07.2026": null,
          "14.07.2026": null,
          "15.07.2026": null,
          "16.07.2026": null,
          "17.07.2026": 178
        },
        {
          "uur": "11:00",
          "12.07.2026": null,
          "13.07.2026": null,
          "14.07.2026": null,
          "15.07.2026": null,
          "16.07.2026": null,
          "17.07.2026": 177
        },
        {
          "uur": "13:00",
          "12.07.2026": 193,
          "13.07.2026": null,
          "14.07.2026": 185,
          "15.07.2026": null,
          "16.07.2026": null,
          "17.07.2026": 177
        },
        {
          "uur": "15:00",
          "12.07.2026": null,
          "13.07.2026": null,
          "14.07.2026": null,
          "15.07.2026": null,
          "16.07.2026": null,
          "17.07.2026": 176
        },
        {
          "uur": "17:00",
          "12.07.2026": null,
          "13.07.2026": null,
          "14.07.2026": null,
          "15.07.2026": null,
          "16.07.2026": null,
          "17.07.2026": 176
        },
        {
          "uur": "19:00",
          "12.07.2026": null,
          "13.07.2026": null,
          "14.07.2026": null,
          "15.07.2026": null,
          "16.07.2026": null,
          "17.07.2026": 176
        },
        {
          "uur": "21:00",
          "12.07.2026": 193,
          "13.07.2026": null,
          "14.07.2026": 183,
          "15.07.2026": null,
          "16.07.2026": null,
          "17.07.2026": 175
        },
        {
          "uur": "23:00",
          "12.07.2026": null,
          "13.07.2026": null,
          "14.07.2026": null,
          "15.07.2026": null,
          "16.07.2026": 181,
          "17.07.2026": 175
        }
      ]
    }
  },
  "nijmegen": {
    "current": 470,
    "forecast_raw": {}
  },
  "maxau_hourly": [
    {
      "t": "13-07 07:30",
      "v": 327
    },
    {
      "t": "13-07 07:45",
      "v": 328
    },
    {
      "t": "13-07 08:00",
      "v": 327
    },
    {
      "t": "13-07 08:15",
      "v": 327
    },
    {
      "t": "13-07 08:30",
      "v": 327
    },
    {
      "t": "13-07 08:45",
      "v": 327
    },
    {
      "t": "13-07 09:00",
      "v": 326
    },
    {
      "t": "13-07 09:15",
      "v": 327
    },
    {
      "t": "13-07 09:30",
      "v": 328
    },
    {
      "t": "13-07 09:45",
      "v": 326
    },
    {
      "t": "13-07 10:00",
      "v": 326
    },
    {
      "t": "13-07 10:15",
      "v": 326
    },
    {
      "t": "13-07 10:30",
      "v": 327
    },
    {
      "t": "13-07 10:45",
      "v": 327
    },
    {
      "t": "13-07 11:00",
      "v": 325
    },
    {
      "t": "13-07 11:15",
      "v": 326
    },
    {
      "t": "13-07 11:30",
      "v": 326
    },
    {
      "t": "13-07 11:45",
      "v": 326
    },
    {
      "t": "13-07 12:00",
      "v": 327
    },
    {
      "t": "13-07 12:15",
      "v": 326
    },
    {
      "t": "13-07 12:30",
      "v": 326
    },
    {
      "t": "13-07 12:45",
      "v": 326
    },
    {
      "t": "13-07 13:00",
      "v": 327
    },
    {
      "t": "13-07 13:15",
      "v": 327
    },
    {
      "t": "13-07 13:30",
      "v": 326
    },
    {
      "t": "13-07 13:45",
      "v": 326
    },
    {
      "t": "13-07 14:00",
      "v": 326
    },
    {
      "t": "13-07 14:15",
      "v": 327
    },
    {
      "t": "13-07 14:30",
      "v": 327
    },
    {
      "t": "13-07 14:45",
      "v": 327
    },
    {
      "t": "13-07 15:00",
      "v": 327
    },
    {
      "t": "13-07 15:15",
      "v": 327
    },
    {
      "t": "13-07 15:30",
      "v": 327
    },
    {
      "t": "13-07 15:45",
      "v": 327
    },
    {
      "t": "13-07 16:00",
      "v": 327
    },
    {
      "t": "13-07 16:15",
      "v": 327
    },
    {
      "t": "13-07 16:30",
      "v": 329
    },
    {
      "t": "13-07 16:45",
      "v": 328
    },
    {
      "t": "13-07 17:00",
      "v": 330
    },
    {
      "t": "13-07 17:15",
      "v": 329
    },
    {
      "t": "13-07 17:30",
      "v": 329
    },
    {
      "t": "13-07 17:45",
      "v": 328
    },
    {
      "t": "13-07 18:00",
      "v": 328
    },
    {
      "t": "13-07 18:15",
      "v": 330
    },
    {
      "t": "13-07 18:30",
      "v": 330
    },
    {
      "t": "13-07 18:45",
      "v": 330
    },
    {
      "t": "13-07 19:00",
      "v": 330
    },
    {
      "t": "13-07 19:15",
      "v": 330
    }
  ]
}